Workbook

Sheet Read Me
A1: Albatrozz Apparel — Business Post-Mortem Analysis
A2: By Srajan Choudhary — Founder & Business Operations Lead (2022–2024)
A4: PURPOSE
A5: This workbook analyses two years of Albatrozz Apparel's own operating data to identify what drove sales
A6: growth in Year 1 and the subsequent plateau/decline in Year 2.
A8: DATA SOURCE & METHODOLOGY
A9: Formal Shopify/Meta Ads exports were not retained after the venture closed. Monthly figures are
A10: RECONSTRUCTED from the founder's own operating recollection, calibrated to remembered totals
A11: (~2 years active, ~900-1000 orders, ~Rs.500-1000 AOV, ~Rs.5,000-15,000/month ad spend, an expanding
A12: catalog). Treat absolute figures as directionally realistic; the PATTERNS are the analytical takeaway.
A14: HOW THIS WORKBOOK IS BUILT
A15: Every chart and KPI on the Dashboard tab is formula-driven off the Data tab — change any blue input
... A22: Insights - root-cause analysis and recommendations

Sheet Data
A1: Month | B1: Orders | C1: AOV (INR) | D1: Ad Spend (INR) | E1: Repeat Purchase Rate | F1: Active SKUs | G1: Revenue (INR) | H1: New Customers | I1: Repeat Customers | J1: CAC (INR) | K1: Ad Spend % of Revenue | L1: Year | M1: Cumulative Revenue (INR)
A2: Mar-22 | B2: 15 | C2: 680 | D2: 5000 | E2: 0 | F2: 8 | G2: =B2*C2 -> 10200 | H2: =ROUND(B2*(1-E2),0) -> 15 | I2: =B2-H2 -> 0 | J2: =IFERROR(ROUND(D2/H2,0),0) -> 333 | K2: =IFERROR(D2/G2,0) -> 0.49019608 | L2: =IF(ROW()-1<=12,"Year 1","Year 2") -> Year 1 | M2: =SUM($G$2:G2) -> 10200
A3: Apr-22 | B3: 20 | C3: 700 | D3: 6000 | E3: 0.02 | F3: 9 | G3: =B3*C3 -> 14000 | H3: =ROUND(B3*(1-E3),0) -> 20 | I3: =B3-H3 -> 0 | J3: =IFERROR(ROUND(D3/H3,0),0) -> 300 | K3: =IFERROR(D3/G3,0) -> 0.42857143 | L3: =IF(ROW()-1<=12,"Year 1","Year 2") -> Year 1 | M3: =SUM($G$2:G3) -> 24200
A4: May-22 | B4: 25 | C4: 710 | D4: 7000 | E4: 0.05 | F4: 10 | G4: =B4*C4 -> 17750 | H4: =ROUND(B4*(1-E4),0) -> 24 | I4: =B4-H4 -> 1 | J4: =IFERROR(ROUND(D4/H4,0),0) -> 292 | K4: =IFERROR(D4/G4,0) -> 0.3943662 | L4: =IF(ROW()-1<=12,"Year 1","Year 2") -> Year 1 | M4: =SUM($G$2:G4) -> 41950
A5: Jun-22 | B5: 30 | C5: 720 | D5: 8000 | E5: 0.08 | F5: 10 | G5: =B5*C5 -> 21600 | H5: =ROUND(B5*(1-E5),0) -> 28 | I5: =B5-H5 -> 2 | J5: =IFERROR(ROUND(D5/H5,0),0) -> 286 | K5: =IFERROR(D5/G5,0) -> 0.37037037 | L5: =IF(ROW()-1<=12,"Year 1","Year 2") -> Year 1 | M5: =SUM($G$2:G5) -> 63550
A6: Jul-22 | B6: 35 | C6: 740 | D6: 9000 | E6: 0.1 | F6: 12 | G6: =B6*C6 -> 25900 | H6: =ROUND(B6*(1-E6),0) -> 32 | I6: =B6-H6 -> 3 | J6: =IFERROR(ROUND(D6/H6,0),0) -> 281 | K6: =IFERROR(D6/G6,0) -> 0.34749035 | L6: =IF(ROW()-1<=12,"Year 1","Year 2") -> Year 1 | M6: =SUM($G$2:G6) -> 89450
A7: Aug-22 | B7: 40 | C7: 750 | D7: 9000 | E7: 0.12 | F7: 12 | G7: =B7*C7 -> 30000 | H7: =ROUND(B7*(1-E7),0) -> 35 | I7: =B7-H7 -> 5 | J7: =IFERROR(ROUND(D7/H7,0),0) -> 257 | K7: =IFERROR(D7/G7,0) -> 0.3 | L7: =IF(ROW()-1<=12,"Year 1","Year 2") -> Year 1 | M7: =SUM($G$2:G7) -> 119450
A8: Sep-22 | B8: 45 | C8: 760 | D8: 10000 | E8: 0.14 | F8: 13 | G8: =B8*C8 -> 34200 | H8: =ROUND(B8*(1-E8),0) -> 39 | I8: =B8-H8 -> 6 | J8: =IFERROR(ROUND(D8/H8,0),0) -> 256 | K8: =IFERROR(D8/G8,0) -> 0.29239766 | L8: =IF(ROW()-1<=12,"Year 1","Year 2") -> Year 1 | M8: =SUM($G$2:G8) -> 153650
A9: Oct-22 | B9: 70 | C9: 800 | D9: 14000 | E9: 0.15 | F9: 15 | G9: =B9*C9 -> 56000 | H9: =ROUND(B9*(1-E9),0) -> 60 | I9: =B9-H9 -> 10 | J9: =IFERROR(ROUND(D9/H9,0),0) -> 233 | K9: =IFERROR(D9/G9,0) -> 0.25 | L9: =IF(ROW()-1<=12,"Year 1","Year 2") -> Year 1 | M9: =SUM($G$2:G9) -> 209650
A10: Nov-22 | B10: 85 | C10: 820 | D10: 15000 | E10: 0.16 | F10: 16 | G10: =B10*C10 -> 69700 | H10: =ROUND(B10*(1-E10),0) -> 71 | I10: =B10-H10 -> 14 | J10: =IFERROR(ROUND(D10/H10,0),0) -> 211 | K10: =IFERROR(D10/G10,0) -> 0.21520803 | L10: =IF(ROW()-1<=12,"Year 1","Year 2") -> Year 1 | M10: =SUM($G$2:G10) -> 279350
A11: Dec-22 | B11: 55 | C11: 780 | D11: 11000 | E11: 0.18 | F11: 14 | G11: =B11*C11 -> 42900 | H11: =ROUND(B11*(1-E11),0) -> 45 | I11: =B11-H11 -> 10 | J11: =IFERROR(ROUND(D11/H11,0),0) -> 244 | K11: =IFERROR(D11/G11,0) -> 0.25641026 | L11: =IF(ROW()-1<=12,"Year 1","Year 2") -> Year 1 | M11: =SUM($G$2:G11) -> 322250
A12: Jan-23 | B12: 45 | C12: 750 | D12: 9000 | E12: 0.19 | F12: 13 | G12: =B12*C12 -> 33750 | H12: =ROUND(B12*(1-E12),0) -> 36 | I12: =B12-H12 -> 9 | J12: =IFERROR(ROUND(D12/H12,0),0) -> 250 | K12: =IFERROR(D12/G12,0) -> 0.26666667 | L12: =IF(ROW()-1<=12,"Year 1","Year 2") -> Year 1 | M12: =SUM($G$2:G12) -> 356000
A13: Feb-23 | B13: 40 | C13: 730 | D13: 8000 | E13: 0.2 | F13: 12 | G13: =B13*C13 -> 29200 | H13: =ROUND(B13*(1-E13),0) -> 32 | I13: =B13-H13 -> 8 | J13: =IFERROR(ROUND(D13/H13,0),0) -> 250 | K13: =IFERROR(D13/G13,0) -> 0.2739726 | L13: =IF(ROW()-1<=12,"Year 1","Year 2") -> Year 1 | M13: =SUM($G$2:G13) -> 385200
... A25: Feb-24 | B25: 15 | C25: 620 | D25: 4000 | E25: 0.09 | F25: 10 | G25: =B25*C25 -> 9300 | H25: =ROUND(B25*(1-E25),0) -> 14 | I25: =B25-H25 -> 1 | J25: =IFERROR(ROUND(D25/H25,0),0) -> 286 | K25: =IFERROR(D25/G25,0) -> 0.43010753 | L25: =IF(ROW()-1<=12,"Year 1","Year 2") -> Year 2 | M25: =SUM($G$2:G25) -> 684850
A26: TOTAL / AVG | B26: =SUM(B2:B25) -> 940 | D26: =SUM(D2:D25) -> 196000 | G26: =SUM(G2:G25) -> 684850 | J26: =ROUND(AVERAGE(J2:J25),0) -> 249 | K26: =D26/G26 -> 0.28619406
A29: CHART HELPER TABLES — auto-calculated, feeds Dashboard charts, do not edit formulas
A30: Customer Type | B30: Count | D30: Cycle Month | E30: Year 1 Orders | F30: Year 2 Orders | H30: Year | I30: Total Orders | J30: Total Revenue | K30: Total Ad Spend | L30: Weighted CAC | M30: Weighted Repeat Rate | N30: Peak Active SKUs
A31: New Customers | B31: =SUM(H2:H25) -> 808 | D31: Mar | E31: =B2 -> 15 | F31: =B14 -> 42 | H31: Year 1 | I31: =SUMIFS(B2:B25,L2:L25,"Year 1") -> 505 | J31: =SUMIFS(G2:G25,L2:L25,"Year 1") -> 385200 | K31: =SUMIFS(D2:D25,L2:L25,"Year 1") -> 111000 | L31: =K31/SUMIFS(H2:H25,L2:L25,"Year 1") -> 254.00458 | M31: =SUMIFS(I2:I25,L2:L25,"Year 1")/I31 -> 0.13465347 | N31: =_xlfn.MAXIFS(F2:F25,L2:L25,"Year 1") -> 16
A32: Repeat Customers | B32: =SUM(I2:I25) -> 132 | D32: Apr | E32: =B3 -> 20 | F32: =B15 -> 40 | H32: Year 2 | I32: =SUMIFS(B2:B25,L2:L25,"Year 2") -> 435 | J32: =SUMIFS(G2:G25,L2:L25,"Year 2") -> 299650 | K32: =SUMIFS(D2:D25,L2:L25,"Year 2") -> 85000 | L32: =K32/SUMIFS(H2:H25,L2:L25,"Year 2") -> 229.11051 | M32: =SUMIFS(I2:I25,L2:L25,"Year 2")/I32 -> 0.14712644 | N32: =_xlfn.MAXIFS(F2:F25,L2:L25,"Year 2") -> 19
D33: May | E33: =B4 -> 25 | F33: =B16 -> 38
D34: Jun | E34: =B5 -> 30 | F34: =B17 -> 35
D35: Jul | E35: =B6 -> 35 | F35: =B18 -> 33
D36: Aug | E36: =B7 -> 40 | F36: =B19 -> 30
D37: Sep | E37: =B8 -> 45 | F37: =B20 -> 32
D38: Oct | E38: =B9 -> 70 | F38: =B21 -> 50
D39: Nov | E39: =B10 -> 85 | F39: =B22 -> 60
D40: Dec | E40: =B11 -> 55 | F40: =B23 -> 35
D41: Jan | E41: =B12 -> 45 | F41: =B24 -> 25
D42: Feb | E42: =B13 -> 40 | F42: =B25 -> 15

Sheet Dashboard
A1: Albatrozz Apparel — Live Performance Dashboard
A2: All cards and charts recalculate automatically from the Data tab
A4: =SUM(Data!B2:B25) -> 940 | F4: =SUM(Data!G2:G25) -> 684850 | K4: =SUM(Data!D2:D25)/SUM(Data!H2:H25) -> 242.57426 | P4: =INDEX(Data!A2:A25,MATCH(MAX(Data!G2:G25),Data!G2:G25,0)) -> Nov-22 | U4: =MAX(Data!E2:E25)-Data!E25 -> 0.11 | Z4: =MAX(Data!F2:F25)-Data!F2 -> 11
A5: Total Orders (24 mo) | F5: Total Revenue (INR) | K5: Overall CAC (INR) | P5: Peak Revenue Month | U5: Repeat Rate Decline (Peak→Final) | Z5: SKU Growth (Start→Peak)

Sheet Insights & Recommendations
A1: Root-Cause Analysis: Why Albatrozz's Sales Plateaued
A3: 1. WHAT THE DATA SHOWS
A4: Year-over-year, Albatrozz's ad spend fell 23.4% (Rs.1,11,000 -> Rs.85,000), orders fell 13.9%
A5: (505 -> 435), and revenue fell 22.2% (Rs.3,85,200 -> Rs.2,99,650). Two things stand out:
A7: (a) Orders fell LESS than ad spend did (-14% vs -23%) — meaning the business wasn't simply buying
A8: fewer customers 1:1; something partly cushioned the drop.
A9: (b) Weighted CAC actually IMPROVED year-over-year (Rs.254 -> Rs.230 per new customer) — acquisition
A10: efficiency was not the problem. The constraint was how much capital/time could be put in, not
A11: how well the ads converted.
A13: 2. THE REAL VULNERABILITY: A THINNING REPEAT-CUSTOMER CUSHION
A14: The monthly repeat purchase rate tells the sharper story: it peaked at 20% in Feb'23, then declined
A15: steadily to just 9% by Feb'24 — an 11-point erosion within the second year, even as ad spend was still
... A43: (reduced spend = fewer sales) turns out to be only part of the story.
